openai_wrapi/__init__.py
openai_wrapi/proxy0.py
openai_wrapi/proxy1.py
openai_wrapi/utils.py
openai_wrapi-0.1.8.dist-info/LICENSE
openai_wrapi-0.1.8.dist-info/METADATA
openai_wrapi-0.1.8.dist-info/WHEEL
openai_wrapi-0.1.8.dist-info/top_level.txt
openai_wrapi-0.1.8.dist-info/RECORD
