Metadata-Version: 2.1
Name: openai-wrapi
Version: 0.1.8
Summary: OpenAI API proxy for fine-grained cost tracking & control and caching of responses
Author: Robert Dargavel Smith
Author-email: teticio@gmail.com
Platform: any
Classifier: Development Status :: 4 - Beta
Classifier: Programming Language :: Python
Classifier: Programming Language :: Python :: 3
Classifier: Programming Language :: Python :: 3.10
License-File: LICENSE
Requires-Dist: requests-aws4auth
Requires-Dist: boto3
Requires-Dist: openai
Requires-Dist: packaging
